{
  "how_to_apply": [
    {
      "step": 1,
      "title": "पात्रता की जांच",
      "detail": "सबसे पहले सुनिश्चित करें कि आप असम के स्थायी निवासी हैं और आपके पास घर खरीदने के लिए बैंक से ऋण लेने की पात्रता है।"
    },
    {
      "step": 2,
      "title": "आवश्यक दस्तावेज तैयार करें",
      "detail": "अपना आधार कार्ड, निवास प्रमाण पत्र (जैसे राशन कार्ड या वोटर आईडी) और आय प्रमाण पत्र (सैलरी स्लिप या आईटीआर) तैयार रखें।"
    },
    {
      "step": 3,
      "title": "बैंक से संपर्क करें",
      "detail": "अपने नजदीकी किसी भी सरकारी या निजी बैंक की शाखा में जाएं और 'Aponar Apon Ghar' योजना के तहत होम लोन के लिए आवेदन करने की इच्छा जताएं।"
    },
    {
      "step": 4,
      "title": "आवेदन फॉर्म भरें",
      "detail": "बैंक द्वारा प्रदान किए गए आवेदन पत्र को भरें और सभी आवश्यक दस्तावेजों की फोटोकॉपी के साथ जमा करें।"
    },
    {
      "step": 5,
      "title": "सत्यापन और स्वीकृति",
      "detail": "बैंक आपके दस्तावेजों का सत्यापन करेगा और पात्रता के आधार पर सब्सिडी के साथ आपका होम लोन स्वीकृत करेगा।"
    }
  ],
  "use_case": {
    "name": "राजेश",
    "age": 30,
    "occupation": "निजी कंपनी कर्मचारी",
    "state": "असम",
    "story": "राजेश ने गुवाहाटी में अपने छोटे से परिवार के लिए घर खरीदने का सपना देखा था। उन्होंने 'Aponar Apon Ghar' योजना के बारे में स्थानीय बैंक शाखा से पता किया और ₹15 लाख का लोन लिया, जिस पर उन्हें सरकार की ओर से ब्याज में भारी सब्सिडी मिली, जिससे उनकी मासिक किस्त काफी कम हो गई।"
  },
  "tips": [
    "आवेदन करने से पहले अपने बैंक मैनेजर से सब्सिडी की वर्तमान ब्याज दरों के बारे में स्पष्ट जानकारी लें।",
    "अपने आय प्रमाण पत्र को अपडेट रखें ताकि लोन स्वीकृति में कोई देरी न हो।",
    "योजना के तहत मिलने वाली सब्सिडी का लाभ सीधे आपके लोन खाते में आता है, इसलिए बैंक के साथ अपना केवाईसी अपडेट रखें।"
  ],
  "common_mistakes": [
    "अधूरे दस्तावेज जमा करना, जिससे आवेदन प्रक्रिया में देरी हो सकती है।",
    "आय प्रमाण पत्र और बैंक रिकॉर्ड में दी गई जानकारी का मेल न खाना।"
  ]
}