{
  "how_to_apply": [
    {
      "step": 1,
      "title": "आधिकारिक अधिसूचना की जाँच",
      "detail": "अपने जिले के मुख्य शिक्षा अधिकारी (CEO) कार्यालय या शिक्षा विभाग की आधिकारिक वेबसाइट पर Rajiv Gandhi Navodaya Vidyalaya प्रवेश परीक्षा की अधिसूचना देखें।"
    },
    {
      "step": 2,
      "title": "आवेदन पत्र प्राप्त करना",
      "detail": "संबंधित स्कूल या ब्लॉक संसाधन केंद्र से आवेदन पत्र प्राप्त करें या ऑनलाइन पोर्टल से डाउनलोड करें।"
    },
    {
      "step": 3,
      "title": "दस्तावेजों का संकलन",
      "detail": "छात्र का आधार कार्ड, उत्तराखंड का मूल निवास प्रमाण पत्र और अभिभावक का आय प्रमाण पत्र तैयार रखें।"
    },
    {
      "step": 4,
      "title": "आवेदन जमा करना",
      "detail": "पूर्ण रूप से भरे हुए आवेदन पत्र को आवश्यक दस्तावेजों के साथ अपने नजदीकी ब्लॉक शिक्षा अधिकारी (BEO) कार्यालय में जमा करें।"
    },
    {
      "step": 5,
      "title": "प्रवेश परीक्षा में भाग लेना",
      "detail": "आवेदन के बाद जारी एडमिट कार्ड के आधार पर निर्धारित तिथि पर प्रवेश परीक्षा दें, जिसके बाद मेरिट के आधार पर चयन होगा।"
    }
  ],
  "use_case": {
    "name": "रमेश",
    "age": 30,
    "occupation": "किसान",
    "state": "उत्तराखंड",
    "story": "रमेश ने अपने बेटे के उज्ज्वल भविष्य के लिए Rajiv Gandhi Navodaya Vidyalaya में आवेदन किया। चयन होने के बाद, उनके बेटे को मुफ्त शिक्षा, भोजन और आवास मिला, जिससे रमेश के सालाना लगभग ₹60,000 के निजी स्कूल के खर्च की बचत हुई।"
  },
  "tips": [
    "प्रवेश परीक्षा के लिए पिछले वर्षों के प्रश्न पत्रों का अभ्यास करें, क्योंकि चयन पूरी तरह मेरिट पर आधारित है।",
    "आय प्रमाण पत्र को नवीनतम रखें ताकि आरक्षण या प्राथमिकता के दावों में कोई समस्या न हो।",
    "फॉर्म भरते समय सभी विवरण आधार कार्ड के अनुसार ही भरें ताकि भविष्य में सत्यापन में देरी न हो।"
  ],
  "common_mistakes": [
    "अंतिम तिथि का इंतजार करना, जिससे अक्सर आवेदन प्रक्रिया छूट जाती है।",
    "अधूरे दस्तावेज जमा करना, जिसके कारण आवेदन पत्र बिना किसी सूचना के रद्द हो सकता है।"
  ]
}