{
  "how_to_apply": [
    {
      "step": 1,
      "title": "पंजीकरण की जांच",
      "detail": "सुनिश्चित करें कि आप छत्तीसगढ़ भवन एवं अन्य सन्निर्माण कर्मकार कल्याण मंडल में एक सक्रिय पंजीकृत निर्माण श्रमिक हैं।"
    },
    {
      "step": 2,
      "title": "दस्तावेजों का संकलन",
      "detail": "आधार कार्ड, निवास प्रमाण पत्र, आय प्रमाण पत्र और श्रमिक पंजीयन कार्ड की स्व-प्रमाणित प्रतियां तैयार रखें।"
    },
    {
      "step": 3,
      "title": "आवेदन पत्र प्राप्त करना",
      "detail": "अपने नजदीकी श्रम कार्यालय या चॉइस सेंटर (C.H.O.I.C.E) पर जाकर Minimata Mahtari Jatan Yojana का आवेदन फॉर्म प्राप्त करें।"
    },
    {
      "step": 4,
      "title": "फॉर्म जमा करना",
      "detail": "पूर्ण रूप से भरे हुए फॉर्म को आवश्यक दस्तावेजों के साथ संबंधित श्रम निरीक्षक या श्रम कार्यालय में जमा करें।"
    },
    {
      "step": 5,
      "title": "सत्यापन और भुगतान",
      "detail": "अधिकारियों द्वारा दस्तावेजों के सत्यापन के बाद, स्वीकृत राशि सीधे आपके बैंक खाते में DBT के माध्यम से भेज दी जाएगी।"
    }
  ],
  "use_case": {
    "name": "सुनीता",
    "age": 30,
    "occupation": "निर्माण श्रमिक (लेबर)",
    "state": "छत्तीसगढ़",
    "story": "रायपुर की निर्माण श्रमिक सुनीता ने अपने श्रमिक कार्ड के माध्यम से Minimata Mahtari Jatan Yojana के बारे में जाना। उन्होंने गर्भावस्था के दौरान आवेदन किया और उन्हें पोषण व चिकित्सा सहायता के रूप में ₹20,000 की आर्थिक मदद सीधे उनके बैंक खाते में प्राप्त हुई, जिससे उन्हें काफी राहत मिली।"
  },
  "tips": [
    "आवेदन करते समय अपने बैंक खाते को आधार से लिंक (NPCI मैपिंग) जरूर करवाएं ताकि भुगतान में देरी न हो।",
    "हमेशा अपने श्रमिक पंजीयन कार्ड का नवीनीकरण समय पर कराते रहें, अन्यथा लाभ मिलने में बाधा आ सकती है।",
    "आवेदन की रसीद जरूर लें और अपने पास सुरक्षित रखें ताकि आप भविष्य में आवेदन की स्थिति ट्रैक कर सकें।"
  ],
  "common_mistakes": [
    "अधूरे दस्तावेज जमा करना, जिससे आवेदन बिना किसी सूचना के रद्द हो सकता है।",
    "बैंक खाते में नाम और श्रमिक कार्ड में नाम का अलग-अलग होना, जिसके कारण भुगतान अटक जाता है।"
  ]
}