{
  "how_to_apply": [
    {
      "step": 1,
      "title": "मंगल दल का गठन और पंजीकरण",
      "detail": "सबसे पहले अपने गांव के युवाओं को संगठित करें और एक 'मंगल दल' बनाएं। इसे संबंधित जिला युवा कल्याण अधिकारी (District Youth Welfare Officer) कार्यालय में पंजीकृत कराएं।"
    },
    {
      "step": 2,
      "title": "दस्तावेजों का संकलन",
      "detail": "अपने आधार कार्ड, मूल निवास प्रमाण पत्र, आय प्रमाण पत्र और मंगल दल के बैंक खाते का विवरण तैयार रखें।"
    },
    {
      "step": 3,
      "title": "आवेदन पत्र प्राप्त करना",
      "detail": "अपने ब्लॉक या जिले के युवा कल्याण विभाग के कार्यालय में जाकर 'Financial Assistance to Youth Groups' योजना का आवेदन फॉर्म प्राप्त करें।"
    },
    {
      "step": 4,
      "title": "प्रोजेक्ट रिपोर्ट जमा करना",
      "detail": "18 चिन्हित व्यावसायिक क्षेत्रों में से किसी एक का चयन करें और एक विस्तृत प्रोजेक्ट रिपोर्ट (DPR) तैयार करके आवेदन पत्र के साथ कार्यालय में जमा करें।"
    },
    {
      "step": 5,
      "title": "सत्यापन और स्वीकृति",
      "detail": "विभाग द्वारा आपके मंगल दल और प्रोजेक्ट की जांच की जाएगी। सत्यापन के बाद, स्वीकृत राशि सीधे मंगल दल के बैंक खाते में स्थानांतरित कर दी जाएगी।"
    }
  ],
  "use_case": {
    "name": "राजेश",
    "age": 30,
    "occupation": "कृषि और डेयरी उद्यमी",
    "state": "उत्तराखंड",
    "story": "राजेश ने अपने गांव के युवाओं के साथ मिलकर एक मंगल दल बनाया और 'Financial Assistance to Youth Groups' योजना के तहत डेयरी फार्मिंग के लिए आवेदन किया। विभाग से ₹50,000 की वित्तीय सहायता पाकर उन्होंने आधुनिक उपकरण खरीदे, जिससे अब उनका समूह हर महीने ₹15,000 का अतिरिक्त मुनाफा कमा रहा है।"
  },
  "tips": [
    "आवेदन करने से पहले अपने ब्लॉक के युवा कल्याण अधिकारी से मिलकर उन 18 क्षेत्रों की सूची जरूर लें जिनमें सहायता दी जा रही है।",
    "प्रोजेक्ट रिपोर्ट (DPR) को स्थानीय बाजार की मांग के अनुसार तैयार करें ताकि स्वीकृति मिलने में आसानी हो।",
    "मंगल दल का बैंक खाता हमेशा 'संयुक्त खाता' (Joint Account) के रूप में ही खुलवाएं।"
  ],
  "common_mistakes": [
    "मंगल दल का पंजीकरण समय पर रिन्यू न कराना, जिससे आवेदन रद्द हो सकता है।",
    "अधूरे दस्तावेज जमा करना या प्रोजेक्ट रिपोर्ट में व्यावसायिक व्यवहार्यता (feasibility) का स्पष्ट न होना।"
  ]
}