{
  "how_to_apply": [
    {
      "step": 1,
      "title": "पात्रता की जाँच",
      "detail": "सुनिश्चित करें कि आपका संगठन (NGO) 'Grant-In-Aid to Voluntary Organizations Working In The Area of Disabled Welfare' के तहत पंजीकृत है और छत्तीसगढ़ समाज कल्याण विभाग के मानदंडों को पूरा करता है।"
    },
    {
      "step": 2,
      "title": "दस्तावेजों का संकलन",
      "detail": "आधार कार्ड, निवास प्रमाण पत्र, आय प्रमाण पत्र, संस्था का पंजीकरण प्रमाण पत्र, और विकलांगता से संबंधित सभी आवश्यक रिपोर्ट तैयार रखें।"
    },
    {
      "step": 3,
      "title": "आवेदन पोर्टल पर पंजीकरण",
      "detail": "छत्तीसगढ़ सरकार के समाज कल्याण विभाग की आधिकारिक वेबसाइट पर जाएं और संस्था के विवरण के साथ ऑनलाइन आवेदन प्रक्रिया शुरू करें।"
    },
    {
      "step": 4,
      "title": "दस्तावेज जमा करना",
      "detail": "ऑनलाइन फॉर्म भरने के बाद, सभी सत्यापित दस्तावेजों की हार्ड कॉपी अपने जिले के जिला विकलांगता पुनर्वास केंद्र (DDRC) या समाज कल्याण कार्यालय में जमा करें।"
    },
    {
      "step": 5,
      "title": "सत्यापन और स्वीकृति",
      "detail": "विभाग द्वारा आपके केंद्र का भौतिक सत्यापन किया जाएगा। सफल सत्यापन के बाद, अनुदान राशि सीधे संस्था के बैंक खाते में स्थानांतरित कर दी जाएगी।"
    }
  ],
  "use_case": {
    "name": "आर्यन",
    "age": 30,
    "occupation": "समाजसेवी",
    "state": "छत्तीसगढ़",
    "story": "आर्यन ने रायपुर में एक विशेष स्कूल चलाया और 'Grant-In-Aid to Voluntary Organizations Working In The Area of Disabled Welfare' के बारे में जिला समाज कल्याण कार्यालय से जाना। उन्होंने आवेदन किया और बच्चों की शिक्षा और पुनर्वास के लिए ₹5 लाख का अनुदान प्राप्त किया, जिससे स्कूल में आधुनिक उपकरण लगाए गए।"
  },
  "tips": [
    "आवेदन जमा करने से पहले अपने सभी दस्तावेजों को नोटरी से सत्यापित करवा लें ताकि प्रक्रिया में देरी न हो।",
    "संस्था का ऑडिट रिपोर्ट और पिछले तीन वर्षों का वित्तीय विवरण हमेशा अद्यतित रखें, यह अनुदान स्वीकृति के लिए अनिवार्य है।",
    "स्थानीय जिला समाज कल्याण अधिकारी के साथ नियमित संपर्क बनाए रखें ताकि आवेदन की स्थिति की जानकारी समय पर मिल सके।"
  ],
  "common_mistakes": [
    "अधूरे दस्तावेज जमा करना, विशेष रूप से संस्था के पंजीकरण और पिछले वित्तीय वर्षों के ऑडिट रिपोर्ट में कमी।",
    "आवेदन फॉर्म में गलत बैंक खाता विवरण देना, जिसके कारण अनुदान राशि के हस्तांतरण में समस्या आती है।"
  ]
}