{
  "how_to_apply": [
    {
      "step": 1,
      "title": "निकटतम आंगनवाड़ी केंद्र की पहचान करें",
      "detail": "अपने क्षेत्र के स्थानीय आंगनवाड़ी केंद्र (Anganwadi Centre) पर जाएं। यह आपके गांव या मोहल्ले में स्थित होता है।"
    },
    {
      "step": 2,
      "title": "आंगनवाड़ी कार्यकर्ता से संपर्क करें",
      "detail": "वहां की आंगनवाड़ी कार्यकर्ता (AWC) से मिलें और Integrated Child Development Services- Uttarakhand योजना के अंतर्गत पंजीकरण के लिए आवेदन पत्र मांगें।"
    },
    {
      "step": 3,
      "title": "आवश्यक दस्तावेज तैयार करें",
      "detail": "अपना आधार कार्ड, निवास प्रमाण पत्र और आय प्रमाण पत्र की फोटोकॉपी तैयार रखें। बच्चे का जन्म प्रमाण पत्र भी साथ ले जाएं।"
    },
    {
      "step": 4,
      "title": "आवेदन पत्र जमा करें",
      "detail": "भरे हुए आवेदन पत्र को सभी दस्तावेजों के साथ आंगनवाड़ी कार्यकर्ता के पास जमा करें। वे आपके विवरण को रजिस्टर में दर्ज करेंगी।"
    },
    {
      "step": 5,
      "title": "सेवाओं का लाभ उठाएं",
      "detail": "पंजीकरण के बाद, आपको नियमित स्वास्थ्य जांच, टीकाकरण और अनुपूरक पोषण (Supplementary Nutrition) मिलना शुरू हो जाएगा।"
    }
  ],
  "use_case": {
    "name": "सुनीता",
    "age": 30,
    "occupation": "गृहिणी",
    "state": "उत्तराखंड",
    "story": "सुनीता ने अपनी आशा कार्यकर्ता से Integrated Child Development Services- Uttarakhand के बारे में सुना। उन्होंने अपने 2 साल के बच्चे और अपनी गर्भावस्था के लिए पंजीकरण कराया, जिससे उन्हें हर महीने लगभग ₹1500 मूल्य का पौष्टिक आहार और नियमित मुफ्त स्वास्थ्य जांच मिली, जिससे उनके परिवार के स्वास्थ्य खर्चों में काफी बचत हुई।"
  },
  "tips": [
    "हमेशा अपने साथ आधार कार्ड की मूल प्रति रखें ताकि सत्यापन में देरी न हो।",
    "आंगनवाड़ी केंद्र द्वारा आयोजित 'सुपोषण दिवस' या स्वास्थ्य शिविरों में अनिवार्य रूप से भाग लें।",
    "यदि आपको पोषण सामग्री मिलने में देरी हो रही है, तो अपने क्षेत्र के बाल विकास परियोजना अधिकारी (CDPO) कार्यालय में शिकायत दर्ज करें।"
  ],
  "common_mistakes": [
    "आय प्रमाण पत्र को पुराना या एक्सपायर्ड जमा करना, जिससे आवेदन रद्द हो सकता है।",
    "आंगनवाड़ी केंद्र में नियमित रूप से उपस्थित न होना, जिससे नाम सूची से हटाया जा सकता है।"
  ]
}