{
  "how_to_apply": [
    {
      "step": 1,
      "title": "पात्रता और पोर्टल की जाँच",
      "detail": "सबसे पहले ICMR की आधिकारिक वेबसाइट (icmr.nic.in) पर जाएं और ICMR- Post Doctoral Fellowship के लिए अपनी पात्रता (Ph.D./MD/MS डिग्री) सुनिश्चित करें।"
    },
    {
      "step": 2,
      "title": "दस्तावेजों की तैयारी",
      "detail": "अपने आधार कार्ड, निवास प्रमाण पत्र, आय प्रमाण पत्र, और अपनी शैक्षणिक डिग्री (Ph.D./MD/MS) की स्कैन की हुई प्रतियां तैयार रखें।"
    },
    {
      "step": 3,
      "title": "शोध प्रस्ताव (Research Proposal) तैयार करना",
      "detail": "किसी ICMR संस्थान या केंद्र के साथ मिलकर एक ठोस शोध प्रस्ताव तैयार करें, क्योंकि आवेदन के लिए एक मेंटर (Mentor) का होना अनिवार्य है।"
    },
    {
      "step": 4,
      "title": "ऑनलाइन आवेदन",
      "detail": "ICMR के समर्पित पोर्टल पर जाकर पंजीकरण करें और सभी आवश्यक विवरण भरें। अपने शोध प्रस्ताव और अन्य दस्तावेजों को निर्धारित प्रारूप में अपलोड करें।"
    },
    {
      "step": 5,
      "title": "सबमिशन और ट्रैकिंग",
      "detail": "आवेदन फॉर्म को अंतिम रूप से सबमिट करें और भविष्य के संदर्भ के लिए आवेदन संख्या (Application ID) का प्रिंटआउट सुरक्षित रख लें।"
    }
  ],
  "use_case": {
    "name": "राजेश",
    "age": 29,
    "occupation": "बायोमेडिकल रिसर्चर",
    "state": "उत्तर प्रदेश",
    "story": "राजेश ने हाल ही में अपनी Ph.D. पूरी की थी और वह संक्रामक रोगों पर शोध करना चाहते थे। उन्होंने ICMR- Post Doctoral Fellowship के लिए आवेदन किया और चयनित होने के बाद उन्हें प्रति माह ₹58,000 की फेलोशिप राशि के साथ-साथ वार्षिक आकस्मिक अनुदान के रूप में ₹3 लाख प्राप्त हुए, जिससे उनका शोध कार्य सफल रहा।"
  },
  "tips": [
    "आवेदन करने से पहले किसी ICMR संस्थान के वरिष्ठ वैज्ञानिक से संपर्क करें ताकि आपका शोध प्रस्ताव संस्थान की प्राथमिकताओं के अनुरूप हो।",
    "अपने शोध प्रस्ताव में नवाचार (Innovation) और सामाजिक प्रभाव पर विशेष जोर दें, क्योंकि चयन प्रक्रिया में इसे प्राथमिकता दी जाती है।",
    "आवेदन की अंतिम तिथि का इंतजार न करें, क्योंकि तकनीकी समस्याओं से बचने के लिए कम से कम एक सप्ताह पहले फॉर्म जमा करना बेहतर होता है।"
  ],
  "common_mistakes": [
    "अधूरे या गलत शोध प्रस्ताव को जमा करना, जिससे आवेदन तुरंत खारिज हो सकता है।",
    "आवश्यक दस्तावेजों (जैसे आय या निवास प्रमाण) को स्पष्ट रूप से स्कैन न करना, जिससे सत्यापन में देरी होती है।"
  ]
}