{
  "how_to_apply": [
    {
      "step": 1,
      "title": "पात्रता की जांच",
      "detail": "सबसे पहले सुनिश्चित करें कि आप गुजरात के एक अनुसूचित जनजाति (ST) सदस्य हैं और अंतर्देशीय मत्स्य पालन (Inland Fisheries) गतिविधियों में सक्रिय हैं।"
    },
    {
      "step": 2,
      "title": "दस्तावेज़ तैयार करना",
      "detail": "अपने आधार कार्ड, निवास प्रमाण पत्र, आय प्रमाण पत्र, जाति प्रमाण पत्र और बैंक खाते की पासबुक की स्व-सत्यापित प्रतियां तैयार रखें।"
    },
    {
      "step": 3,
      "title": "आवेदन पत्र प्राप्त करना",
      "detail": "अपने निकटतम जिला मत्स्य पालन कार्यालय (District Fisheries Office) पर जाएं और 'To Increase Fish Seed Production and Inland Fisheries Resources in Tribal Areas: Boat Net - Gujarat' योजना का आवेदन फॉर्म प्राप्त करें।"
    },
    {
      "step": 4,
      "title": "आवेदन जमा करना",
      "detail": "पूर्ण रूप से भरे हुए फॉर्म को सभी आवश्यक दस्तावेजों के साथ संबंधित मत्स्य पालन विभाग के अधिकारी के पास जमा करें और पावती रसीद (Acknowledgement Receipt) जरूर लें।"
    },
    {
      "step": 5,
      "title": "सत्यापन और लाभ",
      "detail": "विभाग द्वारा आपके आवेदन और दस्तावेजों का सत्यापन किया जाएगा। सफल सत्यापन के बाद, नाव और जाल खरीदने के लिए वित्तीय सहायता सीधे आपके बैंक खाते में भेज दी जाएगी।"
    }
  ],
  "use_case": {
    "name": "रमेश भाई",
    "age": 30,
    "occupation": "मछुआरा",
    "state": "गुजरात",
    "story": "रमेश भाई ने अपने गांव के सरपंच से 'To Increase Fish Seed Production and Inland Fisheries Resources in Tribal Areas: Boat Net - Gujarat' योजना के बारे में सुना। उन्होंने जिला कार्यालय में आवेदन किया और सत्यापन के बाद उन्हें ₹25,000 की वित्तीय सहायता प्राप्त हुई, जिससे उन्होंने एक नई नाव और मजबूत जाल खरीदा। अब उनकी दैनिक मछली पकड़ने की क्षमता बढ़ गई है और उनकी आय में काफी सुधार हुआ है।"
  },
  "tips": [
    "आवेदन जमा करने से पहले अपने सभी दस्तावेजों की कम से कम दो फोटोकॉपी अपने पास सुरक्षित रखें।",
    "मत्स्य पालन विभाग के स्थानीय कार्यालय में जाकर योजना की नवीनतम दिशानिर्देशों (Guidelines) के बारे में जानकारी लें।",
    "सुनिश्चित करें कि आपका बैंक खाता आधार से लिंक हो ताकि सहायता राशि मिलने में कोई देरी न हो।"
  ],
  "common_mistakes": [
    "जाति प्रमाण पत्र का पुराना या अमान्य होना आवेदन को रद्द करवा सकता है।",
    "आवेदन फॉर्म में अधूरी जानकारी भरना या गलत बैंक विवरण देना, जिससे भुगतान में समस्या हो सकती है।"
  ]
}