{
  "how_to_apply": [
    {
      "step": 1,
      "title": "दस्तावेजों की तैयारी",
      "detail": "सबसे पहले अपना आधार कार्ड, सिक्किम का वैध निवास प्रमाण पत्र (Certificate of Identification), और आय प्रमाण पत्र तैयार करें। साथ ही, 80% से अधिक विकलांगता दर्शाने वाला मेडिकल बोर्ड का प्रमाण पत्र अनिवार्य है।"
    },
    {
      "step": 2,
      "title": "आवेदन फॉर्म प्राप्त करना",
      "detail": "अपने नजदीकी जिला समाज कल्याण अधिकारी (District Social Welfare Officer - DSWO) के कार्यालय में जाएं और 'Indira Gandhi National Disability Pension Scheme' का आवेदन पत्र प्राप्त करें।"
    },
    {
      "step": 3,
      "title": "आवेदन फॉर्म भरना",
      "detail": "फॉर्म में अपनी व्यक्तिगत जानकारी, बैंक खाता विवरण (आधार से लिंक होना चाहिए) और विकलांगता का विवरण सही-सही भरें।"
    },
    {
      "step": 4,
      "title": "दस्तावेज जमा करना",
      "detail": "भरे हुए फॉर्म के साथ सभी आवश्यक दस्तावेजों की स्व-सत्यापित फोटोकॉपी संलग्न करें और इसे संबंधित DSWO कार्यालय या ग्राम पंचायत स्तर पर जमा करें।"
    },
    {
      "step": 5,
      "title": "सत्यापन और स्वीकृति",
      "detail": "अधिकारियों द्वारा आपके दस्तावेजों का सत्यापन किया जाएगा। सफल सत्यापन के बाद, पेंशन राशि सीधे आपके बैंक खाते में स्थानांतरित कर दी जाएगी।"
    }
  ],
  "use_case": {
    "name": "कर्मा",
    "age": 30,
    "occupation": "कृषि मजदूर",
    "state": "सिक्किम",
    "story": "दक्षिण सिक्किम के रहने वाले कर्मा, जो 85% दिव्यांग हैं, को अपने गांव के पंचायत सचिव से IGNDPS के बारे में पता चला। उन्होंने अपना मेडिकल सर्टिफिकेट और आधार जमा किया, जिसके बाद उन्हें हर महीने ₹1000 की पेंशन मिलनी शुरू हुई, जिससे उन्हें अपनी बुनियादी जरूरतों को पूरा करने में बहुत मदद मिली।"
  },
  "tips": [
    "सुनिश्चित करें कि आपका बैंक खाता आधार से लिंक हो (DBT के लिए), अन्यथा भुगतान में देरी हो सकती है।",
    "मेडिकल बोर्ड द्वारा जारी विकलांगता प्रमाण पत्र (UDID कार्ड) की कॉपी जरूर रखें, यह सत्यापन प्रक्रिया को तेज करता है।",
    "आवेदन जमा करने के बाद संबंधित कार्यालय से एक पावती रसीद (Acknowledgement Receipt) अवश्य लें।"
  ],
  "common_mistakes": [
    "आय प्रमाण पत्र में गलत जानकारी देना, जिससे आवेदन खारिज हो सकता है।",
    "बैंक खाते का विवरण गलत देना या खाते का सक्रिय न होना, जिससे सरकारी सहायता राशि ट्रांसफर नहीं हो पाती।"
  ]
}