{
  "how_to_apply": [
    {
      "step": 1,
      "title": "दस्तावेजों की तैयारी",
      "detail": "सबसे पहले अपना आधार कार्ड, निवास प्रमाण पत्र, आय प्रमाण पत्र, बीपीएल सूची का प्रमाण और पति का मृत्यु प्रमाण पत्र तैयार रखें।"
    },
    {
      "step": 2,
      "title": "आवेदन पत्र प्राप्त करना",
      "detail": "अपने नजदीकी ब्लॉक विकास अधिकारी (BDO) कार्यालय या अनुमंडल कार्यालय में जाकर Indira Gandhi National Widow Pension Scheme- Bihar का आवेदन फॉर्म प्राप्त करें।"
    },
    {
      "step": 3,
      "title": "फॉर्म भरना",
      "detail": "आवेदन फॉर्म को ध्यानपूर्वक भरें और अपनी बैंक खाता संख्या (जो आधार से लिंक हो) का विवरण सही-सही दर्ज करें।"
    },
    {
      "step": 4,
      "title": "दस्तावेज जमा करना",
      "detail": "भरे हुए फॉर्म के साथ सभी आवश्यक दस्तावेजों की फोटोकॉपी संलग्न करें और इसे अपने ब्लॉक कार्यालय या आरटीपीएस (RTPS) काउंटर पर जमा करें।"
    },
    {
      "step": 5,
      "title": "पावती रसीद प्राप्त करना",
      "detail": "फॉर्म जमा करने के बाद वहां से पावती रसीद (Acknowledgement Receipt) जरूर लें ताकि आप अपने आवेदन की स्थिति ट्रैक कर सकें।"
    }
  ],
  "use_case": {
    "name": "सुनीता देवी",
    "age": 45,
    "occupation": "खेतिहर मजदूर",
    "state": "बिहार",
    "story": "सुनीता देवी ने अपने गांव के मुखिया से Indira Gandhi National Widow Pension Scheme- Bihar के बारे में सुना। उन्होंने अपने बीपीएल कार्ड और मृत्यु प्रमाण पत्र के साथ ब्लॉक कार्यालय में आवेदन किया, जिसके बाद उन्हें हर महीने ₹400 की पेंशन सीधे उनके बैंक खाते में मिलनी शुरू हो गई, जिससे उन्हें अपनी दैनिक जरूरतों को पूरा करने में मदद मिली।"
  },
  "tips": [
    "सुनिश्चित करें कि आपका बैंक खाता आधार से लिंक हो (DBT सक्रिय हो), अन्यथा भुगतान में देरी हो सकती है।",
    "आवेदन जमा करने के बाद समय-समय पर ब्लॉक कार्यालय जाकर अपने आवेदन की स्थिति की जांच करते रहें।",
    "अपने सभी दस्तावेजों की एक फाइल बनाकर रखें ताकि भविष्य में नवीनीकरण या सत्यापन के समय आसानी हो।"
  ],
  "common_mistakes": [
    "बैंक खाते का विवरण गलत भरना, जिससे पेंशन की राशि किसी और खाते में जा सकती है।",
    "आय प्रमाण पत्र का पुराना होना या बीपीएल सूची में नाम का न होना, जिसके कारण आवेदन तुरंत खारिज हो जाता है।"
  ]
}