{
  "how_to_apply": [
    {
      "step": 1,
      "title": "आधिकारिक वेबसाइट पर जाएं",
      "detail": "CBIC की आधिकारिक वेबसाइट (cbic.gov.in) पर जाएं और 'Indirect Tax Internship Scheme' से संबंधित नवीनतम अधिसूचना या विज्ञापन खोजें।"
    },
    {
      "step": 2,
      "title": "पात्रता की जांच करें",
      "detail": "सुनिश्चित करें कि आप कानून के छात्र या स्नातक हैं और विभाग द्वारा निर्धारित शैक्षणिक मानदंडों को पूरा करते हैं।"
    },
    {
      "step": 3,
      "title": "दस्तावेज तैयार करें",
      "detail": "अपने आधार कार्ड, निवास प्रमाण पत्र, आय प्रमाण पत्र और शैक्षणिक प्रमाणपत्रों की स्कैन की हुई प्रतियां तैयार रखें।"
    },
    {
      "step": 4,
      "title": "आवेदन पत्र भरें",
      "detail": "निर्धारित प्रारूप में आवेदन पत्र भरें और उसे आवश्यक दस्तावेजों के साथ संबंधित ईमेल आईडी या पते पर भेजें जैसा कि विज्ञापन में उल्लेखित है।"
    },
    {
      "step": 5,
      "title": "चयन प्रक्रिया का पालन करें",
      "detail": "आवेदन जमा करने के बाद, विभाग द्वारा शॉर्टलिस्ट किए जाने की प्रतीक्षा करें। चयनित होने पर आपको साक्षात्कार या ईमेल के माध्यम से सूचित किया जाएगा।"
    }
  ],
  "use_case": {
    "name": "आर्यन",
    "age": 23,
    "occupation": "लॉ का छात्र",
    "state": "दिल्ली",
    "story": "दिल्ली विश्वविद्यालय के अंतिम वर्ष के छात्र आर्यन ने CBIC की वेबसाइट पर Indirect Tax Internship Scheme के बारे में पढ़ा। उसने समय पर आवेदन किया और चयन के बाद उसे 3 महीने तक कानूनी शोध में मदद करने का मौका मिला, जिससे उसे ₹15,000 प्रति माह का स्टाइपेंड भी प्राप्त हुआ और करियर के लिए बहुमूल्य अनुभव मिला।"
  },
  "tips": [
    "आवेदन के साथ अपना विस्तृत और अपडेटेड सीवी (CV) जरूर संलग्न करें, जिसमें आपकी कानूनी शोध क्षमताओं का उल्लेख हो।",
    "CBIC की वेबसाइट पर नियमित रूप से विजिट करें क्योंकि यह इंटर्नशिप साल में विशिष्ट समय पर ही निकलती है।",
    "आवेदन पत्र में अपनी रुचि के क्षेत्र (जैसे जीएसटी या कस्टम्स) का स्पष्ट उल्लेख करें ताकि आपको संबंधित विभाग में काम करने का मौका मिले।"
  ],
  "common_mistakes": [
    "अधिसूचना में दी गई अंतिम तिथि (Deadline) को नजरअंदाज करना और देरी से आवेदन भेजना।",
    "आवेदन पत्र में अधूरे या गलत संपर्क विवरण (मोबाइल नंबर/ईमेल) देना, जिससे चयन के बाद विभाग आपसे संपर्क न कर पाए।"
  ]
}