{
  "how_to_apply": [
    {
      "step": 1,
      "title": "पंजीकरण की पुष्टि",
      "detail": "सुनिश्चित करें कि आप APB&OCWWB के साथ एक सक्रिय पंजीकृत निर्माण श्रमिक हैं। यदि नहीं, तो पहले बोर्ड के साथ अपना पंजीकरण पूरा करें।"
    },
    {
      "step": 2,
      "title": "दस्तावेजों का संग्रह",
      "detail": "अपना आधार कार्ड, निवास प्रमाण पत्र, आय प्रमाण पत्र, और अस्पताल के मेडिकल बिलों की मूल प्रतियां तैयार रखें।"
    },
    {
      "step": 3,
      "title": "आवेदन पत्र प्राप्त करना",
      "detail": "अपने निकटतम श्रम कार्यालय (Labour Office) या APB&OCWWB के आधिकारिक पोर्टल से 'Medical Assistance' योजना का आवेदन फॉर्म प्राप्त करें।"
    },
    {
      "step": 4,
      "title": "फॉर्म जमा करना",
      "detail": "विधिवत भरे हुए फॉर्म को सभी आवश्यक दस्तावेजों के साथ अपने जिले के श्रम कल्याण अधिकारी (Labour Welfare Officer) के कार्यालय में जमा करें।"
    },
    {
      "step": 5,
      "title": "सत्यापन और भुगतान",
      "detail": "अधिकारी आपके दस्तावेजों का सत्यापन करेंगे। सफल सत्यापन के बाद, सहायता राशि सीधे आपके बैंक खाते में हस्तांतरित कर दी जाएगी।"
    }
  ],
  "use_case": {
    "name": "तेनज़िंग",
    "age": 30,
    "occupation": "निर्माण श्रमिक",
    "state": "अरुणाचल प्रदेश",
    "story": "तेनज़िंग ने ईटानगर में एक निर्माण स्थल पर काम करते समय अचानक बीमार होने पर Medical Assistance (APB&OCWWB) के बारे में सुना। उन्होंने अस्पताल के ₹15,000 के बिल जमा किए और श्रम कार्यालय में आवेदन किया, जिसके बाद उन्हें योजना के तहत ₹12,000 की प्रतिपूर्ति मिली, जिससे उनका आर्थिक बोझ कम हो गया।"
  },
  "tips": [
    "अस्पताल में भर्ती होने के दौरान सभी मेडिकल पर्चियों और बिलों को संभाल कर रखें, क्योंकि ये दावे के लिए अनिवार्य हैं।",
    "सुनिश्चित करें कि आपका बैंक खाता आधार से लिंक हो ताकि सहायता राशि मिलने में देरी न हो।",
    "आवेदन जमा करने से पहले श्रम कार्यालय से एक पावती रसीद (acknowledgement receipt) जरूर लें।"
  ],
  "common_mistakes": [
    "अपूर्ण दस्तावेज जमा करना, विशेष रूप से आय प्रमाण पत्र का पुराना होना।",
    "पंजीकरण की सदस्यता का नवीनीकरण न कराना, जिससे आवेदन खारिज हो सकता है।"
  ]
}