{
  "how_to_apply": [
    {
      "step": 1,
      "title": "आंगनवाड़ी केंद्र की पहचान",
      "detail": "सबसे पहले अपने क्षेत्र के नजदीकी आंगनवाड़ी केंद्र पर जाएं और वहां की आंगनवाड़ी कार्यकर्ता (Asha/Anganwadi worker) से संपर्क करें।"
    },
    {
      "step": 2,
      "title": "पात्रता की जांच",
      "detail": "सुनिश्चित करें कि आपके बच्चे की आयु 3 से 6 वर्ष के बीच है, क्योंकि Mukhyamantri Aanchal Amrit Yojana का लाभ केवल इसी आयु वर्ग के बच्चों को मिलता है।"
    },
    {
      "step": 3,
      "title": "दस्तावेजों का एकत्रीकरण",
      "detail": "अपने साथ बच्चे का आधार कार्ड, निवास प्रमाण पत्र (Domicile) और परिवार का आय प्रमाण पत्र तैयार रखें।"
    },
    {
      "step": 4,
      "title": "पंजीकरण प्रक्रिया",
      "detail": "आंगनवाड़ी केंद्र पर जाकर बच्चे का नाम केंद्र के रजिस्टर में दर्ज करवाएं और आवश्यक दस्तावेजों की फोटोकॉपी जमा करें।"
    },
    {
      "step": 5,
      "title": "लाभ प्राप्त करना",
      "detail": "पंजीकरण के बाद, आपका बच्चा सप्ताह में चार दिन केंद्र पर मिलने वाले फोर्टिफाइड और फ्लेवर्ड दूध का लाभ उठाना शुरू कर सकता है।"
    }
  ],
  "use_case": {
    "name": "सुनीता",
    "age": 30,
    "occupation": "घरेलू सहायिका",
    "state": "उत्तराखंड",
    "story": "सुनीता को अपनी 4 साल की बेटी के कुपोषण की चिंता थी, तभी आंगनवाड़ी कार्यकर्ता ने उन्हें Mukhyamantri Aanchal Amrit Yojana के बारे में बताया। उन्होंने तुरंत अपनी बेटी का पंजीकरण कराया, जिससे अब उसे सप्ताह में 4 दिन मुफ्त पौष्टिक दूध मिलता है, जिससे सुनीता के दूध पर होने वाले ₹400-₹500 के मासिक खर्च की बचत हो रही है और बेटी का स्वास्थ्य भी सुधर रहा है।"
  },
  "tips": [
    "हमेशा अपने नजदीकी आंगनवाड़ी केंद्र के समय का ध्यान रखें ताकि बच्चा दूध वितरण के समय पर वहां उपस्थित रहे।",
    "यदि आपके पास आय प्रमाण पत्र नहीं है, तो अपने क्षेत्र के लेखपाल से संपर्क करके इसे जल्द बनवा लें क्योंकि यह सरकारी योजनाओं के लिए अनिवार्य है।",
    "आंगनवाड़ी कार्यकर्ता से नियमित रूप से बच्चे के स्वास्थ्य कार्ड (Health Card) के बारे में अपडेट लेते रहें।"
  ],
  "common_mistakes": [
    "बच्चे का आधार कार्ड अपडेट न रखना, जिससे पंजीकरण में देरी हो सकती है।",
    "आंगनवाड़ी केंद्र पर नियमित रूप से न जाना, जिससे बच्चा योजना के तहत मिलने वाले दूध के लाभ से वंचित रह सकता है।"
  ]
}