{
  "how_to_apply": [
    {
      "step": 1,
      "title": "आधिकारिक वेबसाइट पर जाएं",
      "detail": "सबसे पहले बिहार सरकार के 'e-Kalyan' पोर्टल (medhasoft.bih.nic.in) पर जाएं।"
    },
    {
      "step": 2,
      "title": "पंजीकरण प्रक्रिया",
      "detail": "पोर्टल पर 'Mukhyamantri Balika Protsahan Yojana' लिंक पर क्लिक करें और अपना रजिस्ट्रेशन पूरा करें। इसके लिए अपना रोल नंबर और इंटरमीडिएट परीक्षा के अंक दर्ज करें।"
    },
    {
      "step": 3,
      "title": "दस्तावेज़ अपलोड करें",
      "detail": "अपने आधार कार्ड, निवास प्रमाण पत्र, आय प्रमाण पत्र, बैंक पासबुक और 12वीं की मार्कशीट की स्कैन की हुई प्रतियां पोर्टल पर अपलोड करें।"
    },
    {
      "step": 4,
      "title": "आवेदन सबमिट करें",
      "detail": "सभी जानकारी दोबारा जांचें और 'Final Submit' बटन पर क्लिक करें। सबमिट करने के बाद आवेदन की रसीद का प्रिंट आउट निकाल कर सुरक्षित रख लें।"
    },
    {
      "step": 5,
      "title": "सत्यापन और भुगतान",
      "detail": "आपके द्वारा दी गई जानकारी का शिक्षा विभाग द्वारा सत्यापन किया जाएगा। सफल सत्यापन के बाद, ₹25,000 की प्रोत्साहन राशि सीधे आपके बैंक खाते में भेज दी जाएगी।"
    }
  ],
  "use_case": {
    "name": "अंजलि",
    "age": 19,
    "occupation": "स्नातक छात्रा",
    "state": "बिहार",
    "story": "अंजलि ने बिहार बोर्ड से 12वीं पास करने के बाद अपने कॉलेज के शिक्षकों से Mukhyamantri Balika Protsahan Yojana के बारे में सुना। उसने तुरंत e-Kalyan पोर्टल पर आवेदन किया और सत्यापन के कुछ हफ्तों बाद ही उसे ₹25,000 की राशि प्राप्त हुई, जिससे उसने अपनी आगे की पढ़ाई के लिए लैपटॉप खरीदा।"
  },
  "tips": [
    "सुनिश्चित करें कि आपका बैंक खाता आधार कार्ड से लिंक हो और उसमें DBT (Direct Benefit Transfer) सक्रिय हो।",
    "आवेदन करते समय बैंक खाता छात्रा के नाम पर ही होना चाहिए, संयुक्त खाता (Joint Account) मान्य नहीं होगा।",
    "पोर्टल पर अपना मोबाइल नंबर और ईमेल आईडी वही दें जो सक्रिय हो, ताकि विभाग से मिलने वाली सूचनाएं आप तक पहुँच सकें।"
  ],
  "common_mistakes": [
    "बैंक खाते में नाम और आधार कार्ड पर नाम का अलग-अलग होना, जिससे भुगतान अटक सकता है।",
    "आवेदन फॉर्म भरते समय गलत रोल नंबर या अंक दर्ज करना, जिससे सत्यापन प्रक्रिया में देरी होती है।"
  ]
}