{
  "how_to_apply": [
    {
      "step": 1,
      "title": "आधिकारिक वेबसाइट पर जाएं",
      "detail": "सबसे पहले NPC की आधिकारिक वेबसाइट (npcindia.gov.in) पर जाएं और 'Careers' या 'Internship' सेक्शन को खोजें।"
    },
    {
      "step": 2,
      "title": "दस्तावेजों को तैयार करें",
      "detail": "अपने आधार कार्ड, निवास प्रमाण पत्र, आय प्रमाण पत्र और कॉलेज द्वारा जारी बोनाफाइड सर्टिफिकेट की डिजिटल कॉपी तैयार रखें।"
    },
    {
      "step": 3,
      "title": "आवेदन फॉर्म भरें",
      "detail": "उपलब्ध ऑनलाइन आवेदन फॉर्म को ध्यानपूर्वक भरें और अपनी शैक्षणिक योग्यता की जानकारी सही-सही दर्ज करें।"
    },
    {
      "step": 4,
      "title": "दस्तावेज अपलोड करें",
      "detail": "फॉर्म के साथ मांगे गए सभी आवश्यक दस्तावेजों को स्कैन करके अपलोड करें और आवेदन सबमिट करें।"
    },
    {
      "step": 5,
      "title": "आवेदन की स्थिति ट्रैक करें",
      "detail": "सबमिशन के बाद प्राप्त 'एप्लीकेशन आईडी' को सुरक्षित रखें और समय-समय पर ईमेल या पोर्टल के माध्यम से चयन प्रक्रिया की जांच करते रहें।"
    }
  ],
  "use_case": {
    "name": "आर्यन",
    "age": 22,
    "occupation": "MBA छात्र",
    "state": "उत्तर प्रदेश",
    "story": "आर्यन ने अपने कॉलेज के प्रोफेसर के माध्यम से NPC Students Internship Program के बारे में सुना। उसने समय पर आवेदन किया और चयन होने के बाद उसे 3 महीने की ट्रेनिंग मिली, जिससे उसे ₹15,000 का मासिक स्टाइपेंड भी प्राप्त हुआ और प्रोफेशनल अनुभव मिला।"
  },
  "tips": [
    "आवेदन करने से पहले अपने कॉलेज के प्लेसमेंट सेल से संपर्क करें, वे अक्सर NPC के साथ समन्वय में मदद करते हैं।",
    "अपने रिज्यूमे (Resume) में उन प्रोजेक्ट्स को जरूर हाइलाइट करें जो NPC के कार्यक्षेत्र जैसे उत्पादकता और गुणवत्ता सुधार से संबंधित हों।",
    "आवेदन की अंतिम तिथि का इंतजार न करें, क्योंकि सीटें सीमित होती हैं और पहले आओ-पहले पाओ के आधार पर प्राथमिकता मिल सकती है।"
  ],
  "common_mistakes": [
    "अधूरे या गलत दस्तावेज अपलोड करना, जिससे आवेदन तुरंत खारिज हो सकता है।",
    "आवेदन फॉर्म में ईमेल आईडी और फोन नंबर गलत भरना, जिससे चयन संबंधी सूचनाएं प्राप्त नहीं हो पातीं।"
  ]
}