{
  "how_to_apply": [
    {
      "step": 1,
      "title": "पंजीकरण की जांच",
      "detail": "सबसे पहले यह सुनिश्चित करें कि आपके माता-पिता राजस्थान श्रम विभाग में एक पंजीकृत निर्माण श्रमिक (Construction Worker) हैं और उनके पास वैध श्रमिक कार्ड है।"
    },
    {
      "step": 2,
      "title": "दस्तावेज तैयार करना",
      "detail": "आधार कार्ड, राजस्थान का मूल निवास प्रमाण पत्र, आय प्रमाण पत्र, श्रमिक कार्ड की प्रति और शैक्षणिक योग्यता के प्रमाण पत्र तैयार रखें।"
    },
    {
      "step": 3,
      "title": "पोर्टल पर आवेदन",
      "detail": "राजस्थान सरकार के 'Shramik Kalyan Portal' या 'SSO Rajasthan' पोर्टल पर जाएं और 'Nirman Shramik Avm Unke Aashrit Bacchon Dwara Bhartiya Rajasthan Prashasnik Seva Hetu Aayojit Pratibhabhik Yojana' के विकल्प को चुनें।"
    },
    {
      "step": 4,
      "title": "फॉर्म भरना",
      "detail": "ऑनलाइन आवेदन फॉर्म में अपनी व्यक्तिगत और शैक्षणिक जानकारी भरें और मांगे गए सभी दस्तावेजों की स्कैन कॉपी अपलोड करें।"
    },
    {
      "step": 5,
      "title": "सत्यापन और सबमिशन",
      "detail": "फॉर्म को सबमिट करने के बाद उसका प्रिंट आउट निकालें और अपने नजदीकी श्रम कार्यालय में जमा करें ताकि अधिकारी इसका भौतिक सत्यापन कर सकें।"
    }
  ],
  "use_case": {
    "name": "राहुल",
    "age": 22,
    "occupation": "सिविल सेवा अभ्यर्थी",
    "state": "राजस्थान",
    "story": "जयपुर के एक निर्माण श्रमिक के बेटे राहुल ने अपने पिता के श्रमिक कार्ड के जरिए इस योजना के लिए आवेदन किया। उसे RAS प्रारंभिक परीक्षा उत्तीर्ण करने के बाद कोचिंग और पुस्तकों के लिए ₹1,00,000 की वित्तीय सहायता प्राप्त हुई, जिससे उसका प्रशासनिक सेवा में जाने का सपना साकार हो रहा है।"
  },
  "tips": [
    "आवेदन करने से पहले अपने श्रमिक कार्ड का नवीनीकरण (Renewal) जरूर करवा लें, क्योंकि एक्सपायर कार्ड पर लाभ नहीं मिलता।",
    "अपने बैंक खाते को आधार से लिंक करवाएं और सुनिश्चित करें कि वह DBT के लिए सक्रिय है ताकि पैसा सीधे खाते में आए।",
    "आवेदन की स्थिति को नियमित रूप से SSO पोर्टल पर ट्रैक करते रहें ताकि किसी भी आपत्ति (Objection) का समय पर समाधान हो सके।"
  ],
  "common_mistakes": [
    "अधूरे या धुंधले दस्तावेज अपलोड करना, जिसके कारण आवेदन तुरंत रद्द कर दिया जाता है।",
    "आय प्रमाण पत्र का पुराना होना; हमेशा आवेदन के समय नवीनतम आय प्रमाण पत्र ही संलग्न करें।"
  ]
}