{
  "how_to_apply": [
    {
      "step": 1,
      "title": "पंजीकरण की पुष्टि करें",
      "detail": "सबसे पहले यह सुनिश्चित करें कि आप A&N Islands Building and Other Construction Workers Welfare Board (ANBOCWWB) के साथ एक सक्रिय निर्माण श्रमिक के रूप में पंजीकृत हैं।"
    },
    {
      "step": 2,
      "title": "दस्तावेजों का संकलन",
      "detail": "अपने आधार कार्ड, निवास प्रमाण पत्र (Residential Proof), और आय प्रमाण पत्र की स्व-सत्यापित प्रतियां तैयार रखें।"
    },
    {
      "step": 3,
      "title": "आवेदन पत्र प्राप्त करना",
      "detail": "पोर्ट ब्लेयर स्थित ANBOCWWB के कार्यालय या संबंधित श्रम विभाग (Labour Department) के कार्यालय में जाकर Pension Benefit के लिए निर्धारित आवेदन पत्र प्राप्त करें।"
    },
    {
      "step": 4,
      "title": "फॉर्म जमा करना",
      "detail": "आवेदन पत्र को पूरी तरह भरें और सभी आवश्यक दस्तावेजों को संलग्न करके संबंधित श्रम अधिकारी (Labour Officer) के पास जमा करें।"
    },
    {
      "step": 5,
      "title": "सत्यापन और स्वीकृति",
      "detail": "दस्तावेजों के सत्यापन के बाद, बोर्ड आपकी पात्रता की जांच करेगा और 55 वर्ष की आयु पूरी होने पर पेंशन राशि सीधे आपके बैंक खाते में स्थानांतरित कर दी जाएगी।"
    }
  ],
  "use_case": {
    "name": "रामू",
    "age": 55,
    "occupation": "राजमिस्त्री",
    "state": "अंडमान और निकोबार द्वीप समूह",
    "story": "रामू ने पिछले 15 वर्षों से पोर्ट ब्लेयर में निर्माण कार्य किया है और ANBOCWWB के साथ पंजीकृत थे। 55 वर्ष के होने पर, उन्होंने श्रम विभाग में आवेदन किया और अब उन्हें प्रतिमाह ₹1,000 की पेंशन मिल रही है, जिससे उन्हें बुढ़ापे में आर्थिक सहारा मिला है।"
  },
  "tips": [
    "सुनिश्चित करें कि आपका आधार कार्ड आपके बैंक खाते से लिंक हो (DBT के लिए), ताकि पेंशन राशि मिलने में कोई देरी न हो।",
    "अपने पंजीकरण कार्ड (Identity Card) को हमेशा सुरक्षित रखें, क्योंकि पेंशन आवेदन के समय इसकी मूल प्रति की आवश्यकता हो सकती है।",
    "आवेदन जमा करने के बाद उसकी एक पावती (Acknowledgement Receipt) जरूर लें ताकि आप अपने आवेदन की स्थिति को ट्रैक कर सकें।"
  ],
  "common_mistakes": [
    "आवेदन पत्र में बैंक खाते का विवरण गलत भरना, जिससे भुगतान विफल हो सकता है।",
    "पंजीकरण का नवीनीकरण (Renewal) न कराना; यदि आपका श्रमिक पंजीकरण सक्रिय नहीं है, तो आप पेंशन के पात्र नहीं होंगे।"
  ]
}