{
  "how_to_apply": [
    {
      "step": 1,
      "title": "आधिकारिक पोर्टल पर पंजीकरण",
      "detail": "सबसे पहले गुजरात सरकार के कौशल विकास विभाग की आधिकारिक वेबसाइट या Project Sankalp के समर्पित पोर्टल पर जाएं और 'Candidate Registration' विकल्प चुनें।"
    },
    {
      "step": 2,
      "title": "दस्तावेज़ तैयार करना",
      "detail": "अपने आधार कार्ड, निवास प्रमाण पत्र (डोमिसाइल), और आय प्रमाण पत्र की डिजिटल प्रतियां (स्कैन की हुई) तैयार रखें।"
    },
    {
      "step": 3,
      "title": "फॉर्म भरना",
      "detail": "ऑनलाइन आवेदन पत्र में अपनी व्यक्तिगत जानकारी, शैक्षिक योग्यता और रुचि का क्षेत्र (जैसे मैन्युफैक्चरिंग या आईटी) भरें।"
    },
    {
      "step": 4,
      "title": "दस्तावेज़ अपलोड और सबमिशन",
      "detail": "सभी आवश्यक दस्तावेज अपलोड करें और आवेदन पत्र को सबमिट करें। सबमिट करने के बाद आवेदन संख्या (Application ID) का प्रिंटआउट या स्क्रीनशॉट सुरक्षित रखें।"
    },
    {
      "step": 5,
      "title": "काउंसलिंग और चयन",
      "detail": "आवेदन के बाद, आपको नजदीकी कौशल विकास केंद्र (Skill Development Center) में काउंसलिंग के लिए बुलाया जाएगा, जहाँ आपको अपने मूल दस्तावेज साथ ले जाने होंगे।"
    }
  ],
  "use_case": {
    "name": "रमेश",
    "age": 30,
    "occupation": "अकुशल श्रमिक",
    "state": "गुजरात",
    "story": "अहमदाबाद के रहने वाले रमेश ने स्थानीय रोजगार मेले में Project Sankalp के बारे में सुना। उन्होंने ऑटोमोबाइल सेक्टर में तीन महीने का प्रशिक्षण लिया, जिसके बाद उन्हें एक प्रतिष्ठित कंपनी में ₹18,000 प्रति माह की नौकरी मिली। इस प्रशिक्षण ने न केवल उनकी आय में ₹7,000 की वृद्धि की, बल्कि उन्हें एक सुरक्षित करियर पथ भी प्रदान किया।"
  },
  "tips": [
    "आवेदन करने से पहले अपनी रुचि के अनुसार सेक्टर का चुनाव करें, क्योंकि Project Sankalp में अलग-अलग क्षेत्रों के लिए अलग-अलग प्रशिक्षण केंद्र हैं।",
    "अपने आधार कार्ड को अपने मोबाइल नंबर से लिंक रखें ताकि ओटीपी सत्यापन में कोई समस्या न आए।",
    "प्रशिक्षण के दौरान मिलने वाले अप्रेंटिसशिप स्टाइपेंड के बारे में केंद्र के अधिकारियों से पहले ही स्पष्ट जानकारी ले लें।"
  ],
  "common_mistakes": [
    "आय प्रमाण पत्र पुराना या एक्सपायर्ड होना, जिससे आवेदन रद्द हो सकता है।",
    "पंजीकरण के समय गलत मोबाइल नंबर या ईमेल आईडी देना, जिससे सरकारी सूचनाएं प्राप्त नहीं हो पातीं।"
  ]
}