{
  "how_to_apply": [
    {
      "step": 1,
      "title": "दस्तावेजों को तैयार करें",
      "detail": "सबसे पहले अपना आधार कार्ड, त्रिपुरा का मूल निवास प्रमाण पत्र और आय प्रमाण पत्र (यह दर्शाते हुए कि आपके पास आय का कोई स्रोत नहीं है) तैयार रखें।"
    },
    {
      "step": 2,
      "title": "आवेदन पत्र प्राप्त करें",
      "detail": "अपने नजदीकी जिला समाज कल्याण कार्यालय (District Social Welfare Office) या ब्लॉक कार्यालय में जाकर 'Pension Scheme for Transgender' का आधिकारिक आवेदन पत्र प्राप्त करें।"
    },
    {
      "step": 3,
      "title": "फॉर्म भरें",
      "detail": "आवेदन पत्र में मांगी गई सभी जानकारी सही-सही भरें और अपने बैंक खाते का विवरण (पासबुक की फोटोकॉपी) संलग्न करें ताकि पेंशन सीधे आपके खाते में आए।"
    },
    {
      "step": 4,
      "title": "दस्तावेज जमा करें",
      "detail": "भरे हुए फॉर्म और सभी आवश्यक दस्तावेजों की फोटोकॉपी को संबंधित समाज कल्याण अधिकारी (Social Welfare Officer) के पास जमा करें।"
    },
    {
      "step": 5,
      "title": "सत्यापन और स्वीकृति",
      "detail": "अधिकारी द्वारा आपके दस्तावेजों के सत्यापन के बाद, आपकी पात्रता की पुष्टि की जाएगी और स्वीकृति मिलने पर ₹2,000 की मासिक पेंशन आपके बैंक खाते में आने लगेगी।"
    }
  ],
  "use_case": {
    "name": "अंजली",
    "age": 30,
    "occupation": "स्वतंत्र कलाकार",
    "state": "त्रिपुरा",
    "story": "अंजली को स्थानीय समाज कल्याण कार्यालय से 'Pension Scheme for Transgender' के बारे में पता चला। उन्होंने अपना आय प्रमाण पत्र और आधार जमा किया, जिसके बाद उन्हें हर महीने ₹2,000 की आर्थिक सहायता मिलने लगी, जिससे उन्हें अपनी दैनिक जरूरतों को पूरा करने में काफी मदद मिली।"
  },
  "tips": [
    "आवेदन जमा करते समय पावती रसीद (Acknowledgement Receipt) जरूर मांगें ताकि आप बाद में अपने आवेदन की स्थिति ट्रैक कर सकें।",
    "सुनिश्चित करें कि आपका बैंक खाता आधार से लिंक हो (DBT सक्षम), ताकि पेंशन मिलने में कोई तकनीकी देरी न हो।",
    "यदि आवेदन में कोई समस्या हो, तो अपने क्षेत्र के ट्रांसजेंडर वेलफेयर बोर्ड के प्रतिनिधि से संपर्क करें।"
  ],
  "common_mistakes": [
    "अधूरे दस्तावेज जमा करना, विशेष रूप से आय प्रमाण पत्र का न होना, आवेदन को खारिज करवा सकता है।",
    "बैंक खाते का विवरण गलत देना, जिससे सरकारी सहायता राशि आपके खाते तक नहीं पहुँच पाती।"
  ]
}