{
  "how_to_apply": [
    {
      "step": 1,
      "title": "पंजीकरण और तैयारी",
      "detail": "सबसे पहले अपनी कृषि भूमि के मिट्टी के नमूने (Soil Samples) एकत्र करें। इसके लिए अपने नजदीकी कृषि विभाग के कार्यालय या 'Soil Health Card' पोर्टल पर जाकर पंजीकरण प्रक्रिया की जानकारी लें।"
    },
    {
      "step": 2,
      "title": "दस्तावेजों का संकलन",
      "detail": "अपने आधार कार्ड, निवास प्रमाण पत्र, आय प्रमाण पत्र और भूमि के स्वामित्व से संबंधित दस्तावेजों (खतौनी/जमाबंदी) की फोटोकॉपी तैयार रखें।"
    },
    {
      "step": 3,
      "title": "मिट्टी का नमूना जमा करना",
      "detail": "अपने खेत की मिट्टी के नमूनों को निर्धारित बैग में भरकर अपने ब्लॉक के कृषि विस्तार अधिकारी या स्थानीय मिट्टी परीक्षण प्रयोगशाला (Soil Testing Lab) में जमा करें।"
    },
    {
      "step": 4,
      "title": "पोर्टल पर आवेदन",
      "detail": "आधिकारिक वेबसाइट (soilhealth.dac.gov.in) पर जाकर अपने विवरण के साथ ऑनलाइन आवेदन करें या अपने ग्राम पंचायत के कृषि मित्र की सहायता लें।"
    },
    {
      "step": 5,
      "title": "कार्ड प्राप्त करना",
      "detail": "परीक्षण के बाद, आपको RKVY Soil Health and Fertility कार्ड प्राप्त होगा, जिसमें आपकी मिट्टी की गुणवत्ता और आवश्यक उर्वरकों की सटीक मात्रा लिखी होगी।"
    }
  ],
  "use_case": {
    "name": "रामेश्वर",
    "age": 30,
    "occupation": "किसान",
    "state": "हरियाणा",
    "story": "हरियाणा के रामेश्वर ने अपने खेत में अंधाधुंध यूरिया के प्रयोग से मिट्टी की उर्वरता कम होते देखी। उन्होंने RKVY Soil Health and Fertility योजना के तहत मिट्टी की जांच कराई, जिससे उन्हें पता चला कि उनकी मिट्टी में जिंक की कमी है। सही उर्वरक उपयोग से उनकी लागत में ₹4,000 प्रति एकड़ की बचत हुई और पैदावार में 15% की वृद्धि दर्ज की गई।"
  },
  "tips": [
    "मिट्टी का नमूना लेते समय सतह से 6 इंच नीचे की मिट्टी लें और उसे छाया में सुखाएं, धूप में नहीं।",
    "हर 2-3 साल में अपनी मिट्टी का परीक्षण जरूर करवाएं ताकि पोषक तत्वों के स्तर में बदलाव को ट्रैक किया जा सके।",
    "Soil Health Card में दी गई उर्वरक सिफारिशों का सख्ती से पालन करें, इससे न केवल खर्च कम होगा बल्कि मिट्टी की सेहत भी सुधरेगी।"
  ],
  "common_mistakes": [
    "मिट्टी के नमूने में कंकड़, पत्थर या पौधों की जड़ें छोड़ देना, जिससे रिपोर्ट गलत आ सकती है।",
    "केवल एक ही जगह से नमूना लेना; हमेशा खेत के 5-6 अलग-अलग कोनों से मिट्टी लेकर उसे मिलाकर नमूना तैयार करना चाहिए।"
  ]
}