{
  "how_to_apply": [
    {
      "step": 1,
      "title": "दस्तावेजों की तैयारी",
      "detail": "अपने आधार कार्ड, निवास प्रमाण पत्र, आय प्रमाण पत्र और कॉलेज द्वारा जारी मूल शुल्क रसीद (Fee Receipt) की प्रतियां तैयार रखें।"
    },
    {
      "step": 2,
      "title": "कॉलेज प्रशासन से संपर्क",
      "detail": "अपने संबंधित कॉलेज के प्रशासनिक कार्यालय (Administrative Office) में जाकर 'Refund of Fees' के लिए आवेदन पत्र प्राप्त करें।"
    },
    {
      "step": 3,
      "title": "आवेदन पत्र भरना",
      "detail": "आवेदन फॉर्म में अपनी प्रवेश रद्दीकरण (Cancellation) या कॉलेज छोड़ने का स्पष्ट कारण लिखें और आवश्यक दस्तावेजों को संलग्न करें।"
    },
    {
      "step": 4,
      "title": "दस्तावेज जमा करना",
      "detail": "पूर्ण रूप से भरे हुए आवेदन को कॉलेज के छात्र कल्याण विभाग या संबंधित क्लर्क के पास जमा करें और पावती (Acknowledgment Receipt) अवश्य लें।"
    },
    {
      "step": 5,
      "title": "सत्यापन और रिफंड",
      "detail": "कॉलेज द्वारा दस्तावेजों के सत्यापन के बाद, ₹100 की कटौती करके शेष राशि आपके बैंक खाते में सीधे स्थानांतरित कर दी जाएगी।"
    }
  ],
  "use_case": {
    "name": "आर्यन",
    "age": 20,
    "occupation": "छात्र",
    "state": "मध्य प्रदेश",
    "story": "आर्यन ने भोपाल के एक कॉलेज में ₹25,000 जमा करके प्रवेश लिया था, लेकिन बाद में उसका चयन एक अन्य प्रतिष्ठित संस्थान में हो गया। उसने 'Refund of Fees' योजना के बारे में कॉलेज नोटिस बोर्ड से जाना और आवेदन किया, जिसके बाद ₹100 काटकर उसे ₹24,900 की राशि वापस मिल गई।"
  },
  "tips": [
    "आवेदन जमा करते समय कॉलेज से 'रसीद की फोटोकॉपी' पर मुहर लगवाकर रिसीविंग जरूर लें ताकि भविष्य में ट्रैक कर सकें।",
    "अपना बैंक खाता आधार से लिंक रखें ताकि रिफंड राशि मिलने में कोई तकनीकी देरी न हो।",
    "प्रवेश रद्दीकरण का आवेदन कॉलेज छोड़ने के तुरंत बाद करें, क्योंकि देरी होने पर कॉलेज प्रशासन नियम बदल सकता है।"
  ],
  "common_mistakes": [
    "मूल शुल्क रसीद (Original Fee Receipt) खो देना, जिसके बिना रिफंड प्रक्रिया में काफी कठिनाई होती है।",
    "आवेदन फॉर्म में बैंक खाता विवरण गलत भरना, जिससे रिफंड राशि अटक सकती है।"
  ]
}