{
  "how_to_apply": [
    {
      "step": 1,
      "title": "आधिकारिक पोर्टल पर जाएँ",
      "detail": "सबसे पहले उत्तराखंड सरकार की State Government Health Scheme (Golden Card) की आधिकारिक वेबसाइट पर लॉग इन करें।"
    },
    {
      "step": 2,
      "title": "पंजीकरण फॉर्म भरें",
      "detail": "वेबसाइट पर 'New Registration' विकल्प चुनें और अपनी कर्मचारी आईडी या पेंशनर विवरण के साथ व्यक्तिगत जानकारी भरें।"
    },
    {
      "step": 3,
      "title": "दस्तावेज़ अपलोड करें",
      "detail": "अपने आधार कार्ड, निवास प्रमाण पत्र और आय प्रमाण पत्र की स्कैन की हुई प्रतियां निर्धारित फॉर्मेट में अपलोड करें।"
    },
    {
      "step": 4,
      "title": "सत्यापन प्रक्रिया",
      "detail": "फॉर्म जमा करने के बाद, अपने संबंधित विभाग या कार्यालय में जाकर दस्तावेजों का भौतिक सत्यापन (Physical Verification) करवाएं।"
    },
    {
      "step": 5,
      "title": "गोल्डन कार्ड प्राप्त करें",
      "detail": "सत्यापन सफल होने के बाद, आपका Golden Card डिजिटल रूप में उपलब्ध हो जाएगा जिसे आप डाउनलोड कर प्रिंट ले सकते हैं।"
    }
  ],
  "use_case": {
    "name": "राजेश",
    "age": 30,
    "occupation": "सरकारी शिक्षक",
    "state": "उत्तराखंड",
    "story": "राजेश के पिता को अचानक हृदय संबंधी समस्या हुई, जिसके इलाज का खर्च निजी अस्पताल में ₹2 लाख बताया गया था। राजेश ने अपने विभाग से State Government Health Scheme के बारे में जानकारी ली और अपना Golden Card इस्तेमाल किया, जिससे पूरा ₹2 लाख का इलाज पूरी तरह से मुफ्त हो गया।"
  },
  "tips": [
    "हमेशा अपने Golden Card की एक डिजिटल कॉपी अपने फोन में रखें ताकि आपातकालीन स्थिति में तुरंत उपयोग किया जा सके।",
    "पंजीकरण के समय मोबाइल नंबर वही दें जो आपके आधार कार्ड से लिंक हो, ताकि OTP प्राप्त करने में समस्या न हो।",
    "इलाज के लिए अस्पताल जाने से पहले यह सुनिश्चित कर लें कि वह अस्पताल State Government Health Scheme के पैनल में शामिल है या नहीं।"
  ],
  "common_mistakes": [
    "दस्तावेजों में नाम और जन्मतिथि का आधार कार्ड से मेल न खाना, जिससे आवेदन रद्द हो सकता है।",
    "पंजीकरण के बाद अपने विभाग से आवेदन को फॉरवर्ड (Forward) न करवाना, जिससे कार्ड जारी होने में देरी होती है।"
  ]
}