{
  "how_to_apply": [
    {
      "step": 1,
      "title": "दस्तावेजों का संकलन",
      "detail": "अपने आधार कार्ड, उत्तराखंड राज्य के मूल निवास प्रमाण पत्र, आय प्रमाण पत्र और राज्य आंदोलन के दौरान घायल होने या विकलांगता से संबंधित मेडिकल रिपोर्ट को तैयार करें।"
    },
    {
      "step": 2,
      "title": "आधिकारिक वेबसाइट पर जाना",
      "detail": "उत्तराखंड सरकार के समाज कल्याण विभाग की आधिकारिक वेबसाइट या राज्य आंदोलनकारी पोर्टल पर जाकर Vishesh Samman Pension Yojana के आवेदन फॉर्म को डाउनलोड करें।"
    },
    {
      "step": 3,
      "title": "आवेदन फॉर्म भरना",
      "detail": "फॉर्म में अपनी व्यक्तिगत जानकारी, आंदोलन में भागीदारी का विवरण और अपनी वर्तमान शारीरिक स्थिति (विकलांगता) की सही जानकारी भरें।"
    },
    {
      "step": 4,
      "title": "दस्तावेजों का सत्यापन",
      "detail": "भरे हुए फॉर्म और सभी स्व-सत्यापित दस्तावेजों को अपने जिले के जिला समाज कल्याण अधिकारी (District Social Welfare Officer) के कार्यालय में जमा करें।"
    },
    {
      "step": 5,
      "title": "अनुमोदन और भुगतान",
      "detail": "सत्यापन के बाद, आपकी पात्रता की पुष्टि होने पर ₹20,000 की मासिक पेंशन सीधे आपके बैंक खाते में हस्तांतरित कर दी जाएगी।"
    }
  ],
  "use_case": {
    "name": "रमेश चंद्र",
    "age": 55,
    "occupation": "पूर्व राज्य आंदोलनकारी",
    "state": "उत्तराखंड",
    "story": "रमेश जी राज्य आंदोलन के दौरान गंभीर रूप से घायल हो गए थे और पिछले कई वर्षों से बिस्तर पर थे। उन्होंने स्थानीय समाज कल्याण कार्यालय में Vishesh Samman Pension Yojana के लिए आवेदन किया और अब उन्हें हर महीने ₹20,000 की पेंशन मिल रही है, जिससे उनकी दवाओं और देखभाल का खर्च आसानी से निकल जाता है।"
  },
  "tips": [
    "मेडिकल बोर्ड द्वारा जारी विकलांगता प्रमाण पत्र को साथ रखें, क्योंकि यह आवेदन की सबसे महत्वपूर्ण कड़ी है।",
    "सुनिश्चित करें कि आपका बैंक खाता आधार से लिंक हो ताकि पेंशन की राशि मिलने में कोई तकनीकी बाधा न आए।",
    "आवेदन जमा करने के बाद उसकी पावती (Acknowledgment Receipt) जरूर लें ताकि भविष्य में स्टेटस ट्रैक किया जा सके।"
  ],
  "common_mistakes": [
    "अधूरे या पुराने मेडिकल दस्तावेजों को संलग्न करना, जिससे आवेदन खारिज हो सकता है।",
    "आंदोलन में भागीदारी के साक्ष्य (जैसे जेल जाने का प्रमाण या एफआईआर) को आवेदन के साथ न लगाना।"
  ]
}