{
  "how_to_apply": [
    {
      "step": 1,
      "title": "पात्रता की जांच",
      "detail": "सबसे पहले यह सुनिश्चित करें कि छात्र गुजरात का निवासी है और सरकार द्वारा अधिसूचित चयनित निजी स्कूलों (जैसे Sainik School, Balachadi) में नामांकित है।"
    },
    {
      "step": 2,
      "title": "दस्तावेजों का संकलन",
      "detail": "अपने आधार कार्ड, निवास प्रमाण पत्र (Domicile), जाति प्रमाण पत्र (SC Certificate) और सक्षम अधिकारी द्वारा जारी आय प्रमाण पत्र की प्रतियां तैयार रखें।"
    },
    {
      "step": 3,
      "title": "आधिकारिक पोर्टल पर पंजीकरण",
      "detail": "गुजरात सरकार के 'Digital Gujarat' पोर्टल पर जाएं और 'Special Scholarship to SC Students in Selected Schools' योजना के लिए अपना पंजीकरण पूरा करें।"
    },
    {
      "step": 4,
      "title": "आवेदन फॉर्म भरना",
      "detail": "ऑनलाइन फॉर्म में अपनी शैक्षणिक जानकारी, स्कूल का विवरण और बैंक खाते का विवरण सावधानीपूर्वक भरें और आवश्यक दस्तावेजों को स्कैन करके अपलोड करें।"
    },
    {
      "step": 5,
      "title": "सत्यापन और सबमिशन",
      "detail": "आवेदन जमा करने के बाद उसकी एक प्रिंटेड कॉपी निकालें और स्कूल प्रशासन के माध्यम से संबंधित जिला कल्याण अधिकारी कार्यालय में जमा करें।"
    }
  ],
  "use_case": {
    "name": "रमेश",
    "age": 14,
    "occupation": "छात्र",
    "state": "गुजरात",
    "story": "रमेश के पिता, जो एक छोटे किसान हैं, ने 'Special Scholarship to SC Students in Selected Schools' के बारे में अपने स्कूल के नोटिस बोर्ड से जाना। उन्होंने समय पर आवेदन किया और ₹50,000 की छात्रवृत्ति प्राप्त की, जिससे रमेश की Sainik School, Balachadi की वार्षिक फीस का बोझ पूरी तरह कम हो गया।"
  },
  "tips": [
    "आवेदन करने से पहले अपने स्कूल के प्रधानाचार्य से संपर्क करें, क्योंकि कई बार स्कूल प्रशासन ही पोर्टल पर छात्र का डेटा सत्यापित करता है।",
    "सुनिश्चित करें कि आपका बैंक खाता आधार से लिंक हो और उसमें DBT (Direct Benefit Transfer) सुविधा सक्रिय हो।",
    "आय प्रमाण पत्र नवीनतम वित्तीय वर्ष का होना चाहिए ताकि आवेदन अस्वीकार न हो।"
  ],
  "common_mistakes": [
    "अक्सर छात्र गलत जाति प्रमाण पत्र या पुराना आय प्रमाण पत्र अपलोड कर देते हैं, जिससे आवेदन रद्द हो जाता है।",
    "बैंक खाते का विवरण भरते समय IFSC कोड में गलती करना, जिससे भुगतान में देरी होती है।"
  ]
}