{
  "how_to_apply": [
    {
      "step": 1,
      "title": "दस्तावेज़ तैयार करें",
      "detail": "अपने आधार कार्ड, निवास प्रमाण पत्र, आय प्रमाण पत्र और दिव्यांगता प्रमाण पत्र (UDID कार्ड) की स्व-सत्यापित प्रतियां तैयार रखें।"
    },
    {
      "step": 2,
      "title": "आवेदन पत्र प्राप्त करें",
      "detail": "अपने निकटतम प्रखंड विकास कार्यालय (BDO) या जिला समाज कल्याण कार्यालय (DSWO) में जाकर 'Swami Vivekananda Nishakta Swavlamban Protsahan Yojana' का आवेदन फॉर्म प्राप्त करें।"
    },
    {
      "step": 3,
      "title": "फॉर्म भरें",
      "detail": "आवेदन फॉर्म में अपनी व्यक्तिगत जानकारी, बैंक खाता विवरण और दिव्यांगता का विवरण सही-सही भरें।"
    },
    {
      "step": 4,
      "title": "दस्तावेज़ जमा करें",
      "detail": "भरे हुए फॉर्म को आवश्यक दस्तावेजों के साथ अपने संबंधित प्रखंड कार्यालय या 'झारसेवा' (JharSewa) पोर्टल के माध्यम से ऑनलाइन जमा करें।"
    },
    {
      "step": 5,
      "title": "सत्यापन और स्वीकृति",
      "detail": "अधिकारियों द्वारा आपके दस्तावेजों का सत्यापन किया जाएगा, जिसके बाद पेंशन राशि सीधे आपके बैंक खाते में हस्तांतरित कर दी जाएगी।"
    }
  ],
  "use_case": {
    "name": "रमेश",
    "age": 30,
    "occupation": "दुकान सहायक",
    "state": "झारखंड",
    "story": "रमेश ने अपने स्थानीय पंचायत कार्यालय में 'Swami Vivekananda Nishakta Swavlamban Protsahan Yojana' के बारे में सुना। उसने अपना UDID कार्ड और आय प्रमाण पत्र जमा किया, जिसके बाद उसे हर महीने ₹1,000 की पेंशन मिलनी शुरू हो गई, जिससे उसकी दवाओं और दैनिक खर्चों में बहुत मदद मिली।"
  },
  "tips": [
    "सुनिश्चित करें कि आपका आधार कार्ड आपके बैंक खाते से लिंक (DBT सक्षम) हो ताकि पेंशन मिलने में देरी न हो।",
    "आवेदन जमा करने के बाद उसकी एक पावती रसीद (Acknowledgement Receipt) अवश्य लें और उसे संभाल कर रखें।",
    "यदि आवेदन में कोई समस्या हो, तो अपने क्षेत्र के जन सेवा केंद्र (CSC) की सहायता लें, वे ऑनलाइन फॉर्म भरने में मदद कर सकते हैं।"
  ],
  "common_mistakes": [
    "बैंक खाते का विवरण गलत भरना, जिससे पेंशन राशि का हस्तांतरण विफल हो जाता है।",
    "आय प्रमाण पत्र का पुराना होना या दिव्यांगता प्रमाण पत्र (UDID) का अमान्य होना।"
  ]
}