{
  "how_to_apply": [
    {
      "step": 1,
      "title": "दस्तावेजों की तैयारी",
      "detail": "सबसे पहले अपना आधार कार्ड, निवास प्रमाण पत्र और आय प्रमाण पत्र तैयार रखें। सुनिश्चित करें कि सभी दस्तावेजों में नाम और पता सही हो।"
    },
    {
      "step": 2,
      "title": "निकटतम केंद्र पर संपर्क",
      "detail": "अपने जिले के 'आदिवासी विकास विभाग' (Tribal Development Department) कार्यालय या अपने नजदीकी 'जन सेवा केंद्र' (CSC) पर जाएं।"
    },
    {
      "step": 3,
      "title": "आवेदन फॉर्म प्राप्त करना",
      "detail": "Vanbandhu Kalyan Yojana का आधिकारिक आवेदन पत्र प्राप्त करें। यदि ऑनलाइन पोर्टल उपलब्ध है, तो आधिकारिक वेबसाइट पर जाकर पंजीकरण करें।"
    },
    {
      "step": 4,
      "title": "दस्तावेज जमा करना",
      "detail": "फॉर्म को पूरी तरह भरें और सभी आवश्यक दस्तावेजों की फोटोकॉपी के साथ संबंधित अधिकारी के पास जमा करें।"
    },
    {
      "step": 5,
      "title": "सत्यापन और स्वीकृति",
      "detail": "आवेदन जमा करने के बाद, अधिकारी आपके दस्तावेजों का सत्यापन करेंगे। सफल सत्यापन के बाद, आपको योजना का लाभ मिलना शुरू हो जाएगा।"
    }
  ],
  "use_case": {
    "name": "रमेश भाई",
    "age": 30,
    "occupation": "कृषि और पशुपालन",
    "state": "गुजरात",
    "story": "गुजरात के डांग जिले में रहने वाले रमेश भाई ने ग्राम पंचायत में Vanbandhu Kalyan Yojana के बारे में सुना। उन्होंने आवेदन किया और उन्हें आधुनिक सिंचाई उपकरण और पशुपालन के लिए ₹50,000 की सहायता मिली, जिससे उनकी वार्षिक आय ₹1.2 लाख से बढ़कर ₹2.5 लाख हो गई।"
  },
  "tips": [
    "आवेदन जमा करने से पहले सभी दस्तावेजों की एक स्व-सत्यापित (self-attested) फोटोकॉपी अपने पास सुरक्षित रखें।",
    "स्थानीय सरपंच या ग्राम पंचायत कार्यालय से संपर्क करें, क्योंकि वे अक्सर इस योजना के तहत विशेष शिविर आयोजित करते हैं।",
    "आय प्रमाण पत्र नवीनतम वित्तीय वर्ष का ही होना चाहिए ताकि आवेदन खारिज न हो।"
  ],
  "common_mistakes": [
    "अधूरे दस्तावेज जमा करना, जिससे आवेदन प्रक्रिया में देरी होती है।",
    "आय प्रमाण पत्र में गलत जानकारी देना, जो बाद में सत्यापन के दौरान पकड़ी जा सकती है।"
  ]
}